onegov.foundation-0.4.1-py3.6-nspkg.pth
onegov/foundation/.gitignore
onegov/foundation/__init__.py
onegov/foundation/theme.py
onegov/foundation/upgrade.py
onegov/foundation/foundation/README.md
onegov/foundation/foundation/VERSION
onegov/foundation/foundation/fixes.scss
onegov/foundation/foundation/foundation.scss
onegov/foundation/foundation/normalize.scss
onegov/foundation/foundation/foundation/_functions.scss
onegov/foundation/foundation/foundation/_settings.scss
onegov/foundation/foundation/foundation/components/_accordion.scss
onegov/foundation/foundation/foundation/components/_alert-boxes.scss
onegov/foundation/foundation/foundation/components/_block-grid.scss
onegov/foundation/foundation/foundation/components/_breadcrumbs.scss
onegov/foundation/foundation/foundation/components/_button-groups.scss
onegov/foundation/foundation/foundation/components/_buttons.scss
onegov/foundation/foundation/foundation/components/_clearing.scss
onegov/foundation/foundation/foundation/components/_dropdown-buttons.scss
onegov/foundation/foundation/foundation/components/_dropdown.scss
onegov/foundation/foundation/foundation/components/_flex-video.scss
onegov/foundation/foundation/foundation/components/_forms.scss
onegov/foundation/foundation/foundation/components/_global.scss
onegov/foundation/foundation/foundation/components/_grid.scss
onegov/foundation/foundation/foundation/components/_icon-bar.scss
onegov/foundation/foundation/foundation/components/_inline-lists.scss
onegov/foundation/foundation/foundation/components/_joyride.scss
onegov/foundation/foundation/foundation/components/_keystrokes.scss
onegov/foundation/foundation/foundation/components/_labels.scss
onegov/foundation/foundation/foundation/components/_magellan.scss
onegov/foundation/foundation/foundation/components/_offcanvas.scss
onegov/foundation/foundation/foundation/components/_orbit.scss
onegov/foundation/foundation/foundation/components/_pagination.scss
onegov.foundation-0.4.1.dist-info/DESCRIPTION.rst
onegov.foundation-0.4.1.dist-info/METADATA
onegov.foundation-0.4.1.dist-info/RECORD
onegov.foundation-0.4.1.dist-info/WHEEL
onegov.foundation-0.4.1.dist-info/entry_points.txt
onegov.foundation-0.4.1.dist-info/metadata.json
onegov.foundation-0.4.1.dist-info/namespace_packages.txt
onegov.foundation-0.4.1.dist-info/top_level.txt
