Metadata-Version: 2.0
Name: onegov.foundation
Version: 0.4.1
Summary: Provides a base for Zurb Foundation themes used in OneGov.
Home-page: http://github.com/onegov/onegov.foundation
Author: Seantis GmbH
Author-email: info@seantis.ch
License: GPLv2
Platform: any
Classifier: Intended Audience :: Developers
Classifier: Programming Language :: Python :: 3 :: Only
Classifier: Programming Language :: Python :: 3.6
Classifier: Programming Language :: Python :: 3.7
Classifier: Topic :: Software Development :: Libraries :: Python Modules
Classifier: License :: OSI Approved :: GNU General Public License v2 (GPLv2)
Provides-Extra: test
Requires-Dist: onegov.core
Requires-Dist: libsass
Provides-Extra: test
Requires-Dist: coverage; extra == 'test'
Requires-Dist: pytest; extra == 'test'
